easyhttp/ClientConnection.py
easyhttp/HttpServer.py
easyhttp/Request.py
easyhttp/RequestParser.py
easyhttp/Response.py
easyhttp/SocketServer.py
easyhttp/__init__.py
easyhttp-0.0.5.dist-info/LICENSE
easyhttp-0.0.5.dist-info/METADATA
easyhttp-0.0.5.dist-info/WHEEL
easyhttp-0.0.5.dist-info/top_level.txt
easyhttp-0.0.5.dist-info/RECORD
