Metadata-Version: 2.1
Name: easyhttp
Version: 0.0.5
Summary: Basic HTTP server package
Home-page: UNKNOWN
Author: luisbrandino (Luis Brandino)
Author-email: <luisbrandino.contato@gmail.com>
License: UNKNOWN
Keywords: python,webserver,http,http server,sockets
Platform: UNKNOWN
Classifier: Intended Audience :: Developers
Classifier: Programming Language :: Python :: 3
Classifier: Operating System :: Unix
Classifier: Operating System :: MacOS :: MacOS X
Classifier: Operating System :: Microsoft :: Windows
